[
    {"w_code":"01","ar_name":"أدرار"}, 
    {"w_code":"02","ar_name":"الشلف"}, 
    {"w_code":"03","ar_name":"الأغواط"}, 
    {"w_code":"04","ar_name":"أم البواقي"}, 
    {"w_code":"05","ar_name":" باتنة"}, 
    {"w_code":"06","ar_name":"بجاية"}, 
    {"w_code":"07","ar_name":"بسكرة"}, 
    {"w_code":"08","ar_name":"بشار"}, 
    {"w_code":"09","ar_name":"البليدة"}, 
    {"w_code":"10","ar_name":"البويرة"}, 
    {"w_code":"11","ar_name":"تمنراست"}, 
    {"w_code":"12","ar_name":" تبسة"}, 
    {"w_code":"13","ar_name":"تلمسان"}, 
    {"w_code":"14","ar_name":"تيارت"}, 
    {"w_code":"15","ar_name":"تيزي وزو"}, 
    {"w_code":"16","ar_name":"الجزائر"}, 
    {"w_code":"17","ar_name":" الجلفة"}, 
    {"w_code":"18","ar_name":" جيجل"}, 
    {"w_code":"19","ar_name":" سطيف"}, 
    {"w_code":"20","ar_name":" سعيدة"}, 
    {"w_code":"21","ar_name":"سكيكدة"}, 
    {"w_code":"22","ar_name":"سيدي بلعباس"}, 
    {"w_code":"23","ar_name":" عنابة"}, 
    {"w_code":"24","ar_name":" قالمة"}, 
    {"w_code":"25","ar_name":"قسنطينة"}, 
    {"w_code":"26","ar_name":" المدية"}, 
    {"w_code":"27","ar_name":"مستغانم"}, 
    {"w_code":"28","ar_name":"المسيلة"}, 
    {"w_code":"28","ar_name":"معسكر"}, 
    {"w_code":"30","ar_name":"ورقلة"}, 
    {"w_code":"31","ar_name":"وهران"}, 
    {"w_code":"32","ar_name":"البيض"}, 
    {"w_code":"33","ar_name":"إليزي"}, 
    {"w_code":"34","ar_name":"برج بوعريريج"}, 
    {"w_code":"35","ar_name":"بومرداس"}, 
    {"w_code":"36","ar_name":"الطارف"}, 
    {"w_code":"37","ar_name":"تندوف"}, 
    {"w_code":"38","ar_name":"تسمسيلت"}, 
    {"w_code":"39","ar_name":"الوادي"}, 
    {"w_code":"40","ar_name":"خنشلة"}, 
    {"w_code":"41","ar_name":"سوق أهراس"}, 
    {"w_code":"42","ar_name":"تيبازة"}, 
    {"w_code":"43","ar_name":"ميلة"}, 
    {"w_code":"44","ar_name":"عين الدفلى"}, 
    {"w_code":"45","ar_name":"النعامة"}, 
    {"w_code":"46","ar_name":"عين تموشنت"}, 
    {"w_code":"47","ar_name":"غرداية"}, 
    {"w_code":"48","ar_name":"غليزان"}
]















































